langchain_naver/__init__.py
langchain_naver/chat_models.py
langchain_naver/const.py
langchain_naver/embeddings.py
langchain_naver-0.1.0.dist-info/licenses/LICENSE
langchain_naver-0.1.0.dist-info/METADATA
langchain_naver-0.1.0.dist-info/WHEEL
langchain_naver-0.1.0.dist-info/top_level.txt
langchain_naver-0.1.0.dist-info/RECORD
