Metadata-Version: 2.4
Name: langchain-naver
Version: 0.1.0
Summary: An integration package connecting NaverCloud Clova Studio and LangChain
License: MIT
Requires-Python: <4.0,>=3.9
License-File: LICENSE
Requires-Dist: httpx-sse>=0.4.0
Requires-Dist: langchain-core>=0.3.51
Requires-Dist: langchain-openai>=0.3.12
Dynamic: license-file
